electricity_usage/__init__.py
electricity_usage/__main__.py
electricity_usage/_version.py
electricity_usage/daemon.py
electricity_usage/data_dirs.py
electricity_usage/em_data.py
electricity_usage/job.py
electricity_usage/commands/__init__.py
electricity_usage/commands/area_codes.py
electricity_usage/commands/areas.py
electricity_usage/commands/run.py
electricity_usage/commands/start.py
electricity_usage/commands/status.py
electricity_usage/commands/stop.py
electricity_usage-0.1.1.dist-info/COPYING.md
electricity_usage-0.1.1.dist-info/LICENSE.md
electricity_usage-0.1.1.dist-info/METADATA
electricity_usage-0.1.1.dist-info/WHEEL
electricity_usage-0.1.1.dist-info/entry_points.txt
electricity_usage-0.1.1.dist-info/top_level.txt
electricity_usage-0.1.1.dist-info/RECORD
