Metadata-Version: 2.1
Name: electricity_usage
Version: 0.1.1
Summary: The electricity_usage package provides a scheduler which will kick off processes only when there is a surplus in local energy production. 
Maintainer-email: Tim <holotim@gmail.com>, Nemo <nemo24751@gmail.com>
License: MIT
Classifier: Programming Language :: Python :: 3
Classifier: Operating System :: OS Independent
Classifier: License :: OSI Approved :: MIT License
Requires-Python: >=3.8
License-File: LICENSE.md
License-File: COPYING.md
Requires-Dist: click
Requires-Dist: watchdog
Requires-Dist: requests
Requires-Dist: platformdirs
Requires-Dist: pytimeparse
Provides-Extra: docs
Requires-Dist: ipykernel ; extra == 'docs'
Requires-Dist: nbsphinx ; extra == 'docs'
Requires-Dist: nbsphinx-link ; extra == 'docs'
Requires-Dist: sphinx ; extra == 'docs'
Requires-Dist: sphinx-mdinclude ; extra == 'docs'
Requires-Dist: sphinx-rtd-theme ; extra == 'docs'
Requires-Dist: sphinx-click ; extra == 'docs'
Provides-Extra: tests
Requires-Dist: pytest ; extra == 'tests'
Requires-Dist: mock ; extra == 'tests'
Requires-Dist: pytest-cov ; extra == 'tests'
Requires-Dist: nbval ; extra == 'tests'
